my_fibonacci/__init__.py
my_fibonacci/fibonacci.py
my_test_fibonacci-1.0.1.dist-info/METADATA
my_test_fibonacci-1.0.1.dist-info/WHEEL
my_test_fibonacci-1.0.1.dist-info/top_level.txt
my_test_fibonacci-1.0.1.dist-info/RECORD
