Metadata-Version: 2.1
Name: my-test-fibonacci
Version: 1.0.1
Summary: implementation of fibonacci function
Maintainer: Ru Zhang
Maintainer-email: heavenmarshal@gmail.com
Requires-Python: >=3.7
Requires-Dist: numpy (>=1.21.0)
